{
  "name": "Carrie Sullivan",
  "age": 35,
  "address": {
    "street": "Nicag Parkway",
    "city": "Ezapadpo",
    "state": "MS",
    "zip": "97425"
  },
  "contact": {
    "phone": "(940) 415-9557",
    "servicePhone": "800213352"
  },
  "birthday": "1992-06-23T04:23:15.822Z",
  "ip": "178.78.73.22",
  "foo": "bar",
  "profile": {
    "about": "Imijozuv munku toesab duluvdu bas olwo zo zaliz nom pag seh karku naj roh tubin pusjifoz ohofu. Da veevofi mik sonos bamgefdi lutirlec lug uwuohi im upifaca dulno du fev wahnurvob cahopugu eceaj ca oniwaig. Ot alilovit nir erumi febtujwew loap wunowfa puvogur liv fujhoju var vozad zikenrad du omehir kegmuscuh ciga. Ukomuzdo wuamoci tijnotrug itu nawokca basrojge hufteso cob joci azjep ekela muvoviw moc fahiuw jonjala udubawzun epibo jeb. Vaitoow esgar padi tikamobiv pa golwilu najlub dewo kom di kulzog duv mudbuhak nowi ihucibu asapde.",
    "bio": "Ba do fe pi gulavez calusnes gifif rew afheh uramocuc rillane kigti sufivikil apidivu fiso joltu pajgibje rev. Nepcojso ozfugjak bi vuf bepmu lew ufi tidzo cowuto ob wuehe lajikon pelnat. Oku fiup baso ovsav tihini ji ojotipded pu sahsi zanmu keinjuw ju hushi sotobpuc tujace. Kar riizvel geci jilmuzbin nasubju utide ku ti lic dig pahojgus didsal uwikej sa."
  },
  "apiKey": "844c1e8e5542b73ea0f2d895c37a6d461912a1ea15f1242011acf489c205efb4",
  "currency": {
    "code": "CUP",
    "name": "Cuba Peso"
  }
}