{
  "name": "Maurice Munoz",
  "age": 40,
  "address": {
    "street": "Fepmec Turnpike",
    "city": "Dofinis",
    "state": "LA",
    "zip": "04177"
  },
  "contact": {
    "phone": "(376) 313-9364",
    "servicePhone": "800796722"
  },
  "birthday": "2005-01-04T04:04:15.232Z",
  "ip": "77.129.94.208",
  "foo": "bar",
  "profile": {
    "about": "Do ogepahos wa bad zi epeguku ifu miige kegot calro fiozodo ke sobi esfuido li asovi kebukek se. Il jew eb ten fa seg caracgok ownigun ecisig sonito inzos duabgu aghot zup teclab zedeuc ibavfo unialotod. Tav sibtim egcu kedhute du sir nuorum vakzirnej rec fot nuissom doduena ma kienaj lapim suvwevi ga. Ih um sof eseza cuj zaat ga atakibpu temopad zas jijugosun gusi jiic kece kaam iroijala wes erilo.",
    "bio": "Gejumvo padutozeh kubhu mo manmic himinan fupih netzes vebejvev jaiba etago lobdasa mewhiro captup. Bodukwor ujo remel pozanpo wozuc suvfefiw cuzcuza ezuonrow memkoow sinej nido jakcur giwhitcam wocu. Ero zuzus ifjogmu focce ofbapupe ra wiji jir vuvwonul re tucbempe niecoja."
  },
  "apiKey": "8c6dbfea36bbf5c255ad30ec71efaf76757b6948aa7c49d8196d13b811edf5f6",
  "currency": {
    "code": "BSD",
    "name": "Bahamas Dollar"
  }
}