{
  "name": "Lois Scott",
  "age": 65,
  "address": {
    "street": "Kurir Pass",
    "city": "Nuvemauh",
    "state": "AR",
    "zip": "05414"
  },
  "contact": {
    "phone": "(448) 814-8837",
    "servicePhone": "800638563"
  },
  "birthday": "1987-10-07T01:06:48.814Z",
  "ip": "210.252.47.125",
  "foo": "bar",
  "profile": {
    "about": "Capu woctumab segugcu bafowso muwad cusof suzcidzut gu anuje esinazo cigvujim dalagaif dubez umjegzu vu morummo oksaj. Weiveni pet ressi hesewo cer biod hot fuula ochek pikatob miuj va wi om escubed. Puzbofar zopivi ku je se uhbovom wi juahdi ifu vatmifib simkekmal rote neheja ihgi casot hefico jo sah. Ten tunifa lube pisdo tagke senleclo ijrew hic fiup osgefu hilatis vaz wanejiz vok iczof mursol tav. Paecera zacvub waovegu ve zobnihog okbapjo wuaj ula vohtunuw isiuno holve fi rilug za lujake ucu. Zowfousu virhota tuaf wu fagweadu amuzi bojdicla ikuv cokuc vojzazbol hefasog pum zucaruz curtinza gokaf cu. Zirre rueze jo jufnomri pivalnu bazwujuc womenju ne at wego mu niolbum cadiamo koku lupreso opmuvu ivbe ra.",
    "bio": "Botvuja vefde jip wif feigeowa holdiop usipeuw nir woub ilo cak litcik ja di osekelij. Vegnaw cakcanem ejkoze es otu puvlep cusi ez di omeponuv secajve kawakahi daawe uv agi. Lilda fiklilme jahdedal pibutoet mifucomip ihe mebamadaf mofsez katukgof efomeono ejebagis ahavogu caru tuwuk motol. Jekrauki bug ku iniale erwusjeb iztu tomos lawfu urolopkuw dapu wakezni pamdikbe paseobe itmasa gu labdaz. Zuv ivo teto olegifro pibutgap ikruk wipbi ak akmug wofgu mupirwoj ha. Maza zarigopi pit ono kedpi toame lehnocug hipobur umugonsid ke jop jimzu oglujpo tefva."
  },
  "apiKey": "8bc8397bb45a59b4c42805806936d3552f8a39c6346dbc51a321f96ddde2ad21",
  "currency": {
    "code": "KWD",
    "name": "Kuwait Dinar"
  }
}