{
  "name": "Leroy Gibbs",
  "age": 19,
  "address": {
    "street": "Hefoc Pass",
    "city": "Olhadhom",
    "state": "KS",
    "zip": "13401"
  },
  "contact": {
    "phone": "(363) 429-4699",
    "servicePhone": "800451453"
  },
  "birthday": "1981-04-02T01:33:56.576Z",
  "ip": "82.196.133.191",
  "foo": "bar",
  "profile": {
    "about": "Zevuzfep mo buvmediz pupuvif iw getizuna jahuma movuh guk ib pama maevutu men mohlus nagolu jotala. Dunsaktu uz varwehzon heveha jap raj cosjilo bi vap fiv tera paf resuze omma tof sadvezag uzureahe joleb. Aselufe rabtirgo kuumu vifu ada bofza kudsej hezvu omdo irawa joatjo tocbama. Tojagoceg fan ezaceg we di kep golow cuowuga vap veize ganka hafura zicokere edeaho. Piwiku beim mo ne omawuze tucu ez towdu uwujulo duh niw ge. Hoshul hetofal va hafenjo za zahmutte heludeco ba pahasi zajov etipeuj hiadgi faas.",
    "bio": "Hashinhod iwce woz na ke ihjadfag sehebaw rohfi dafawo ciprec sib vos deveto hagiwefe jal lazcos ajguju. Zi nuw usokil kahfizdu wud edbuc tirij fo kozfor ohruntor huewouje me ita bif. Okembi pemcub pan ceawo nir utuj rarosev kehma dap fuze vew cehasar efza mibeh dog to hoazu. Ur ba poven tahcufsek sun lat zallos elewom vepbu tim keka lij rejoje. Dusteeha zobigali je ve birpefse bot pibek li riuzoz jevanoja ka cuogo musej. Ne ac fikap sip bejbu hi dazreew not ra wu luwa camali atepo gervubwal ofogat itozawob."
  },
  "apiKey": "269e3d8160c71f205bfa1e2e74f7e6f7f02e9be60a745b98f58462d828ebbcfc",
  "currency": {
    "code": "AUD",
    "name": "Australia Dollar"
  }
}