{
  "name": "Jim Bowman",
  "age": 61,
  "address": {
    "street": "Reglil Turnpike",
    "city": "Kaovege",
    "state": "NM",
    "zip": "81730"
  },
  "contact": {
    "phone": "(528) 560-6238",
    "servicePhone": "800529467"
  },
  "birthday": "2000-07-28T06:19:30.637Z",
  "ip": "16.132.142.43",
  "foo": "bar",
  "profile": {
    "about": "Rejrozut tuec rasiji in minuv ja erfemid ohojunow dapwodlu jeelefi luji wivo. Lu wimajolo jesud wa dib oni iduvu darifete kas tagsihva buh tijzersiz ozeikitu atze tu nasvoj ziah. Modbofah gun sajeswu lizaubu sohsigva foznunhe kaab af para zija ju ug babom juuj.",
    "bio": "Ogi lesonusid kupvu pocukcac cegec gi fuwzitro di hoddatug elhig uhi kof akiwobi jecalmop soli guteuhu puidogi. Ziftufafe efu va rimwifo ceb lorseaw eg azbup sosvivja po buramo cicijmif av ov no et. Sevesrok efezus hudwigsed nemo bodpecsig okmi bip wo liulo fittier ega ahoeka jemomijor gisaga kel wus cevtup."
  },
  "apiKey": "82879386ebd36d71b151482e11d904a32da88c779af30bf7a0aeac59b8d39f65",
  "currency": {
    "code": "IDR",
    "name": "Indonesia Rupiah"
  }
}