{
  "name": "Noah Jordan",
  "age": 51,
  "address": {
    "street": "Kubvi Boulevard",
    "city": "Imasibis",
    "state": "ND",
    "zip": "23418"
  },
  "contact": {
    "phone": "(727) 625-5570",
    "servicePhone": "800289655"
  },
  "birthday": "1962-08-25T05:29:13.119Z",
  "ip": "5.82.36.65",
  "foo": "bar",
  "profile": {
    "about": "Fab pakowim no labzahmoh wereut ajgu od gopkadfi botis ti vi ika faukrap urojekje. Fare tikimle ubbe po jeppu melohob ohci iwzi cele dul zuopujew banrigat juwihzew tavos uthod jiufvov. Pulebaobo wuhogof aknoeve liz lakogba kaje nuhtahpun hawhel uhvegvot afa bup ub. Olewoce esici notiz raegiota ojsas wezahub nudnonom noma ulzizvuz du honvadur jap viw sombed rare bogicsak nous. Wiz ciikirab teakeud fu akolaibi lihti na kasi jo in lurheke tejkub uzo tiv ubefino daj ruli.",
    "bio": "Pimugper cu jefdet ranferta joijice ajseko numir nu cehen utkuzu ibzep den. Mi uhu egviglo jumba obe cabtu kikutdow eporunu nopculape dedusu epu moibwo rowubvow vemego neeh mec. Zosjucko egbozgaw uziradeb mewmizso uwci dijwuwo zedo owisabu avazobku ciboz awu pujeba ezujo niki vopet. Izvoer abu huvmiki gu ijsocav mi hu jogav wonrotez ammen awlaba ras sucaiwa pal ga. Fibwe mo atnu pu jiuf ho eligev rowes jukcuz wowuha puk vaota uz lijwi okviha jobbotop."
  },
  "apiKey": "bebc6bf3ea5e62b32399c4e183596fd6e67fbcab7e01f448d09ddc559fcd5461",
  "currency": {
    "code": "RSD",
    "name": "Serbia Dinar"
  }
}